setup.py
service_utils/Service_utils.py
service_utils/__init__.py
service_utils.egg-info/PKG-INFO
service_utils.egg-info/SOURCES.txt
service_utils.egg-info/dependency_links.txt
service_utils.egg-info/top_level.txt