Metadata-Version: 1.1
Name: service-utils
Version: 0.1.1b0
Summary: Python Service Utilities
Home-page: https://www.github.com/sid1057/service_utils/
Author: Ivan Deylid
Author-email: ivanov.dale@gmail.com
License: MIT
Keywords: configuration,configuration-managment,service,microservice,automatization
Platform: linux
Classifier: Development Status :: 2 - Pre-Alpha
Classifier: Operating System :: POSIX
Classifier: Programming Language :: Python
